multidbconfig/__init__.py
multidbconfig/db/conn.py
multidbconfig-0.1.0.dist-info/METADATA
multidbconfig-0.1.0.dist-info/WHEEL
multidbconfig-0.1.0.dist-info/top_level.txt
multidbconfig-0.1.0.dist-info/RECORD
