Metadata-Version: 2.4
Name: multidbconfig
Version: 0.1.0
Summary: Unified interface for MySQL, MongoDB, and SQLite
Author-email: Shradha <prathameshpatil0545@gmail.com>
License: MIT
Classifier: Programming Language :: Python :: 3
Classifier: License :: OSI Approved :: MIT License
Classifier: Operating System :: OS Independent
Requires-Python: >=3.8
Requires-Dist: SQLAlchemy>=1.4
Requires-Dist: pymongo>=4.0
Requires-Dist: pymysql>=1.0
